airflow/providers/oraclethick/provider.yaml
airflow/providers/oraclethick/hooks/oraclethick.py
airflow_providers_oraclethick_hook-0.0.2.dist-info/METADATA
airflow_providers_oraclethick_hook-0.0.2.dist-info/WHEEL
airflow_providers_oraclethick_hook-0.0.2.dist-info/top_level.txt
airflow_providers_oraclethick_hook-0.0.2.dist-info/RECORD
