Metadata-Version: 2.1
Name: airflow-providers-oraclethick-hook
Version: 0.0.2
Summary: Thick driver initialization for oracledb Airflow hook
Home-page: https://github.com/SVESoftware/airflow-providers-oraclethick
Author: Drazen Nezic
Author-email: info@trialogic.hr
Project-URL: Bug Tracker, https://github.com/SVESoftware/airflow-providers-oraclethick/issues
Classifier: Programming Language :: Python :: 3
Classifier: License :: OSI Approved :: MIT License
Classifier: Operating System :: OS Independent
Requires-Python: >=3.8
